target_selection/__init__.py
target_selection/__main__.py
target_selection/cartons/__init__.py
target_selection/cartons/base.py
target_selection/cartons/bhm_aqmes.py
target_selection/cartons/bhm_csc.py
target_selection/cartons/bhm_galaxies.py
target_selection/cartons/bhm_gua.py
target_selection/cartons/bhm_rm.py
target_selection/cartons/bhm_spiders_agn.py
target_selection/cartons/bhm_spiders_clusters.py
target_selection/cartons/guide.py
target_selection/cartons/mwm_bin_gaia.py
target_selection/cartons/mwm_bin_vis.py
target_selection/cartons/mwm_cb.py
target_selection/cartons/mwm_cb_cvcandidates.py
target_selection/cartons/mwm_dust.py
target_selection/cartons/mwm_erosita.py
target_selection/cartons/mwm_galactic.py
target_selection/cartons/mwm_halo.py
target_selection/cartons/mwm_halo_gaia_dr3.py
target_selection/cartons/mwm_hypervelocity.py
target_selection/cartons/mwm_legacy_ir2opt.py
target_selection/cartons/mwm_magcloud_agb.py
target_selection/cartons/mwm_magcloud_rgb.py
target_selection/cartons/mwm_monitor_apogee.py
target_selection/cartons/mwm_more_ob.py
target_selection/cartons/mwm_ob.py
target_selection/cartons/mwm_openfiber.py
target_selection/cartons/mwm_planet.py
target_selection/cartons/mwm_rv.py
target_selection/cartons/mwm_snc.py
target_selection/cartons/mwm_snc_further_ext.py
target_selection/cartons/mwm_tess_ob.py
target_selection/cartons/mwm_tess_rgb.py
target_selection/cartons/mwm_wd.py
target_selection/cartons/mwm_yso.py
target_selection/cartons/ops_apogee_stds.py
target_selection/cartons/ops_boss_stds.py
target_selection/cartons/ops_bright_stars.py
target_selection/cartons/ops_skies.py
target_selection/cartons/skymask.py
target_selection/cartons/too.py
target_selection/cartons/tools.py
target_selection/config/target_selection.yml
target_selection/config/target_selection_v0.yml
target_selection/config/xmatch_v0.yml
target_selection/config/xmatch_v0p5.yml
target_selection/config/xmatch_v1.yml
target_selection/exceptions.py
sdss_target_selection-1.4.4.dist-info/METADATA
sdss_target_selection-1.4.4.dist-info/WHEEL
sdss_target_selection-1.4.4.dist-info/entry_points.txt
sdss_target_selection-1.4.4.dist-info/licenses/LICENSE.md
sdss_target_selection-1.4.4.dist-info/RECORD
