Metadata-Version: 2.4
Name: sdss-target-selection
Version: 1.4.4
Summary: Code to perform target selection for BHM/MWM using catalogdb
License: BSD 3-Clause
License-File: LICENSE.md
Keywords: astronomy,software
Author: José Sánchez-Gallego
Author-email: gallegoj@uw.edu
Requires-Python: >=3.10,<4.0
Classifier: Development Status :: 4 - Beta
Classifier: Intended Audience :: Science/Research
Classifier: License :: Other/Proprietary License
Classifier: Natural Language :: English
Classifier: Operating System :: OS Independent
Classifier: Programming Language :: Python :: 3
Classifier: Programming Language :: Python :: 3.10
Classifier: Programming Language :: Python :: 3.11
Classifier: Programming Language :: Python :: 3.12
Classifier: Programming Language :: Python :: 3.13
Classifier: Programming Language :: Python :: 3.14
Classifier: Topic :: Documentation :: Sphinx
Classifier: Topic :: Software Development :: Libraries :: Python Modules
Requires-Dist: adbc-driver-postgresql
Requires-Dist: astropy (>=5.0.0)
Requires-Dist: click (>=8.0,<9.0)
Requires-Dist: dustmaps (==1.0.10)
Requires-Dist: enlighten (>=1.4.0,<2.0.0)
Requires-Dist: gala (>=1.6.1,<2.0.0)
Requires-Dist: healpy (>=1.18.1)
Requires-Dist: matplotlib (>=3.1.1,<4.0.0)
Requires-Dist: mocpy (>=0.18.0)
Requires-Dist: networkx (>=2.4,<3.0)
Requires-Dist: numpy (>=1,<2)
Requires-Dist: pandas (>=2.0.0,<3.0.0)
Requires-Dist: polars (>=1,<2)
Requires-Dist: pyarrow
Requires-Dist: pydantic (>=2.8.2,<3.0.0)
Requires-Dist: sdss-pymangle (>=0.9.3)
Requires-Dist: sdssdb (==0.13.3)
Requires-Dist: sdsstools (>=1.6.0,<2.0.0)
Requires-Dist: tables (>=3.6.1)
Requires-Dist: typing-extensions (>=4.12.2)
Project-URL: Documentation, https://sdss-target-selection.readthedocs.io/en/latest/
Project-URL: Homepage, https://github.com/sdss/target_selection
Project-URL: Repository, https://github.com/sdss/target_selection
